tina/__init__.py
tina/__main__.py
tina/advans.py
tina/common.py
tina/hacker.py
tina/inject.py
tina/lazimp.py
tina/memory.py
tina/probe.py
tina/random.py
tina/shield.py
tina/skybox.py
tina/assimp/__init__.py
tina/assimp/gltf.py
tina/assimp/obj.py
tina/assimp/pfm.py
tina/assimp/tet.py
tina/cli/__init__.py
tina/cli/mesh.py
tina/cli/particles.py
tina/cli/volume.py
tina/core/__init__.py
tina/core/engine.py
tina/core/lighting.py
tina/core/particle.py
tina/core/shader.py
tina/core/triangle.py
tina/core/volume.py
tina/core/wireframe.py
tina/matr/__init__.py
tina/matr/material.py
tina/matr/nodes.py
tina/matr/wavelen.py
tina/mesh/__init__.py
tina/mesh/base.py
tina/mesh/conn.py
tina/mesh/cull.py
tina/mesh/export.py
tina/mesh/grid.py
tina/mesh/model.py
tina/mesh/norm.py
tina/mesh/prim.py
tina/mesh/simple.py
tina/mesh/trans.py
tina/mesh/wire.py
tina/pars/__init__.py
tina/pars/base.py
tina/pars/export.py
tina/pars/simple.py
tina/pars/trans.py
tina/path/__init__.py
tina/path/bidir.py
tina/path/engine.py
tina/path/geometry.py
tina/path/particle.py
tina/path/tree.py
tina/path/triangle.py
tina/path/volume.py
tina/postp/__init__.py
tina/postp/blooming.py
tina/postp/denoise.py
tina/postp/fxaa.py
tina/postp/ssao.py
tina/postp/ssr.py
tina/postp/tonemap.py
tina/scene/__init__.py
tina/scene/raster.py
tina/scene/tracer.py
tina/util/__init__.py
tina/util/_mciso_data.py
tina/util/accumator.py
tina/util/control.py
tina/util/matrix.py
tina/util/mciso.py
tina/util/stack.py
tina/voxl/__init__.py
tina/voxl/base.py
tina/voxl/scale.py
tina/voxl/simple.py
tina/voxl/trans.py
tina_blend/__init__.py
tina_blend/node_system.py
tina_blend/render_engine.py
taichi_tina-0.1.1.dist-info/LICENSE
taichi_tina-0.1.1.dist-info/METADATA
taichi_tina-0.1.1.dist-info/WHEEL
taichi_tina-0.1.1.dist-info/top_level.txt
taichi_tina-0.1.1.dist-info/RECORD
