Metadata-Version: 2.1
Name: taichi-tina
Version: 0.1.1
Summary: A real-time soft renderer based on the Taichi programming language
Home-page: https://github.com/taichi-dev/taichi_three
Author: archibate
Author-email: 1931127624@qq.com
License: MIT
Keywords: graphics,renderer
Platform: UNKNOWN
Classifier: Intended Audience :: Developers
Classifier: Intended Audience :: Science/Research
Classifier: Topic :: Multimedia :: Graphics
Classifier: Topic :: Games/Entertainment :: Simulation
Classifier: Operating System :: OS Independent
Requires-Python: >=3.6
Requires-Dist: taichi
